<?xml version="1.0" encoding="utf-8" ?><dwsync><file name="configure copy.js" server="mcduffie.dreamhost.com//modernistcat.com/" local="3383967600" remote="20563836784" /><file name="configure.js" server="mcduffie.dreamhost.com//modernistcat.com/" local="3426390000" remote="20606259184" /><file name="configure1.js" server="mcduffie.dreamhost.com//modernistcat.com/" local="3383967600" remote="20563836784" /><file name="configure_fut.js" server="mcduffie.dreamhost.com//modernistcat.com/" local="3383967600" remote="20563836784" /><file name="jquery-1.4.2.min.js" server="mcduffie.dreamhost.com//modernistcat.com/" local="3426390000" remote="20606259184" /><file name="jquery-ui-1.8.1.custom.min.js" server="mcduffie.dreamhost.com//modernistcat.com/" local="3426390000" remote="20606259184" /><file name="jquery.effects.blind.min.js" server="mcduffie.dreamhost.com//modernistcat.com/" local="3383967600" remote="20563836784" /><file name="jquery.effects.core.min.js" server="mcduffie.dreamhost.com//modernistcat.com/" local="3383967600" remote="20563836784" /><file name="jquery.effects.scale.min.js" server="mcduffie.dreamhost.com//modernistcat.com/" local="3383967600" remote="20563836784" /><file name="jquery.localscroll-1.2.7-min.js" server="mcduffie.dreamhost.com//modernistcat.com/" local="3426390000" remote="20606259184" /><file name="jquery.scrollTo-1.4.2-min.js" server="mcduffie.dreamhost.com//modernistcat.com/" local="3426390000" remote="20606259184" /><file name="jquery.tools-home.min.js" server="mcduffie.dreamhost.com//modernistcat.com/" local="3426390000" remote="20606259184" /><file name="jquery.tools.min.js" server="mcduffie.dreamhost.com//modernistcat.com/" local="3426390000" remote="20606259184" /><file name="jquery.ui.button.min.js" server="mcduffie.dreamhost.com//modernistcat.com/" local="3426390000" remote="20606259184" /><file name="jquery.ui.core.min.js" server="mcduffie.dreamhost.com//modernistcat.com/" local="3383967600" remote="20563836784" /><file name="jquery.ui.dialog.min.js" server="mcduffie.dreamhost.com//modernistcat.com/" local="3426390000" remote="20606259184" /><file name="jquery.ui.mouse.min.js" server="mcduffie.dreamhost.com//modernistcat.com/" local="3383967600" remote="20563836784" /><file name="jquery.ui.position.min.js" server="mcduffie.dreamhost.com//modernistcat.com/" local="3383967600" remote="20563836784" /><file name="jquery.ui.slider.min.js" server="mcduffie.dreamhost.com//modernistcat.com/" local="3383967600" remote="20563836784" /><file name="jquery.ui.widget.min.js" server="mcduffie.dreamhost.com//modernistcat.com/" local="3383967600" remote="20563836784" /><file name="page_setup.js" server="mcduffie.dreamhost.com//modernistcat.com/" local="3426390000" remote="20606259184" /><file name="ui.selectmenu.js" server="mcduffie.dreamhost.com//modernistcat.com/" local="3426390000" remote="20606259184" /></dwsync>